sistema_bancario/__init__.py
sistema_bancario/cliente.py
sistema_bancario/conta.py
sistema_bancario/conta_corrente.py
sistema_bancario/deposito.py
sistema_bancario/historico.py
sistema_bancario/main.py
sistema_bancario/pessoa_fisica.py
sistema_bancario/saque.py
sistema_bancario/transacao.py
higwind0_sys_bank-3.0.1.dist-info/METADATA
higwind0_sys_bank-3.0.1.dist-info/WHEEL
higwind0_sys_bank-3.0.1.dist-info/entry_points.txt
higwind0_sys_bank-3.0.1.dist-info/top_level.txt
higwind0_sys_bank-3.0.1.dist-info/RECORD
