Metadata-Version: 2.4
Name: Higwind0-sys-bank
Version: 3.0.1
Summary: Sistema bancário simples em Python usando POO
Author: Fernando Mafaciolli
Author-email: mafaciolli@outlook.com
Classifier: Programming Language :: Python :: 3
Classifier: Operating System :: OS Independent
Requires-Python: >=3.8
Dynamic: author
Dynamic: author-email
Dynamic: classifier
Dynamic: description
Dynamic: description-content-type
Dynamic: requires-python
Dynamic: summary
